dab_live_api/__init__.py
dab_live_api/const.py
dab_live_api/examples/getting_started.py
dab_live_api-0.0.2.dist-info/LICENSE
dab_live_api-0.0.2.dist-info/METADATA
dab_live_api-0.0.2.dist-info/WHEEL
dab_live_api-0.0.2.dist-info/top_level.txt
dab_live_api-0.0.2.dist-info/RECORD
