Metadata-Version: 2.1
Name: dab_live_api
Version: 0.0.2
Author-email: Domenico Blanco <domenicog.blanco@gmail.com>
License: GNU GENERAL PUBLIC LICENSE
Requires-Python: >=3.12
License-File: LICENSE
Requires-Dist: aiohttp
